logger_python/__init__.py
logger_python/base_logger.py
logger_python/default_logger.py
logger_python/logging.py
logger_python/multi_logger.py
logger_python/conf/__init__.py
logger_python/conf/logit_conf.py
logger_python/conf/logit_multi_conf.py
synapse_logger-1.0.1.dist-info/METADATA
synapse_logger-1.0.1.dist-info/WHEEL
synapse_logger-1.0.1.dist-info/top_level.txt
synapse_logger-1.0.1.dist-info/RECORD
