Metadata-Version: 2.4
Name: synapse-logger
Version: 1.0.1
Summary: A common logger library.
Requires-Python: >=3.8
Dynamic: requires-python
Dynamic: summary
